zeroshotlabs/__init__.py
zeroshotlabs/main.py
zeroshotlabs-0.1.12.dist-info/METADATA
zeroshotlabs-0.1.12.dist-info/WHEEL
zeroshotlabs-0.1.12.dist-info/top_level.txt
zeroshotlabs-0.1.12.dist-info/RECORD
